{
  "genres": [
    {
      "name": "科幻",
      "pairs": [
        {
          "source": { "title": "星际穿越", "year": "2014", "tmdbId": 157336 },
          "recommend": { "title": "降临", "year": "2016", "tmdbId": 329865 },
          "reason": "如果你被《星际穿越》中时间悖论与情感内核的交织所震撼，《降临》用同样的硬科幻外壳包裹着关于语言、宿命与存在主义的深邃思辨。维伦纽瓦以沉静的镜头语言讲述了一个与时间对话的故事，结局的情感冲击力不输前者。"
        },
        {
          "source": { "title": "盗梦空间", "year": "2010", "tmdbId": 27205 },
          "recommend": { "title": "源代码", "year": "2011", "tmdbId": 45612 },
          "reason": "《盗梦空间》让你在层层梦境中迷失方向，而《源代码》用更紧凑的篇幅构建了另一场关于意识与真实的心灵迷局。十分钟的循环反复重置，每一次都离真相更近一步——如果你喜欢烧脑设定与情感内核并重的叙事，这部科幻悬疑片会让你欲罢不能。"
        },
        {
          "source": { "title": "银翼杀手2049", "year": "2017", "tmdbId": 335984 },
          "recommend": { "title": "湮灭", "year": "2018", "tmdbId": 300668 },
          "reason": "《银翼杀手2049》的压抑美学与存在主义追问，在《湮灭》中得到了更极致的自然主义转化。通过神秘的「闪晃」区域探讨自我毁灭与重生，视觉奇观背后是对人类意识本质的恐怖拷问。如果你着迷于前者那种沉重而诗意的科幻气质，这部小众佳作会让你回味无穷。"
        },
        {
          "source": { "title": "火星救援", "year": "2015", "tmdbId": 286217 },
          "recommend": { "title": "月球", "year": "2009", "tmdbId": 17431 },
          "reason": "《火星救援》中主角在绝境中依靠科学与幽默生存下去，而《月球》用更沉静克制的方式讲述了一个人在月球基地上与孤独对抗的故事。两部作品都聚焦于宇航员面对极端环境时的冷静与坚韧，但后者多了一层关于身份与记忆的哲学追问。"
        },
        {
          "source": { "title": "沙丘", "year": "2021", "tmdbId": 438631 },
          "recommend": { "title": "异星灾变", "year": "2020", "tmdbId": 106651 },
          "reason": "宏大史诗与宗教寓言——这是《沙丘》与《异星灾变》共享的独特气质。雷德利·斯科特监制的这部科幻剧集在荒凉的外星上展开关于人工智能、信仰与人类起源的深邃叙事，视觉风格冷峻肃穆，与《沙丘》的末世美学一脉相承。"
        }
      ]
    },
    {
      "name": "悬疑",
      "pairs": [
        {
          "source": { "title": "禁闭岛", "year": "2010", "tmdbId": 11324 },
          "recommend": { "title": "记忆碎片", "year": "2000", "tmdbId": 77 },
          "reason": "《禁闭岛》让你从头到尾质疑什么是真实，而《记忆碎片》将这种对记忆的怀疑推向了更极致的结构实验。诺兰用倒叙手法让你亲历失忆者的认知困境，每一段记忆都是一块拼图，而最终的真相会让你脊背发凉。"
        },
        {
          "source": { "title": "致命魔术", "year": "2006", "tmdbId": 1124 },
          "recommend": { "title": "完美陌生人", "year": "2016", "tmdbId": 404632 },
          "reason": "《致命魔术》告诉我们每一个魔术背后都有残酷的代价，而《完美陌生人》用一场朋友聚餐中的手机游戏揭开了人际关系中最隐秘的角落。前者是悬疑魔术师，后者是人性解剖刀——如果你享受真相层层剥开那一刻的震撼力，这部意大利电影会让你欲罢不能。"
        },
        {
          "source": { "title": "穆赫兰道", "year": "2001", "tmdbId": 1018 },
          "recommend": { "title": "睁开你的双眼", "year": "1997", "tmdbId": 555 },
          "reason": "大卫·林奇的《穆赫兰道》是好莱坞梦魇的终极影像化，而《睁开你的双眼》用相似的笔触模糊了梦境与现实的边界。它是《香草天空》的原版，但更晦涩、更实验、更大胆。如果你沉迷于林奇式的叙事诡计，这部西班牙心理惊悚片会让你反复解读。"
        }
      ]
    },
    {
      "name": "恐怖",
      "pairs": [
        {
          "source": { "title": "遗传厄运", "year": "2018", "tmdbId": 493922 },
          "recommend": { "title": "圣鹿之死", "year": "2017", "tmdbId": 399248 },
          "reason": "《遗传厄运》的家庭创伤与超自然恐怖让人不寒而栗，而《圣鹿之死》用希腊悲剧的结构包裹了一个现代心理惊悚故事。导演欧格斯·兰斯莫斯以标志性的怪异镜头语言营造出持续累积的不安感，比任何jump scare都更令人窒息。"
        },
        {
          "source": { "title": "灯塔", "year": "2019", "tmdbId": 503919 },
          "recommend": { "title": "女巫", "year": "2015", "tmdbId": 333339 },
          "reason": "《灯塔》与《女巫》出自同一位导演罗伯特·艾格斯之手，共享对历史质感和心理恐怖的极致追求。前者在孤岛上见证人逐渐疯魔，后者在新英格兰荒野中目睹信仰被蚕食——两部作品都是慢热但后劲极大的当代恐怖经典，适合喜欢氛围大于惊吓的观众。"
        }
      ]
    },
    {
      "name": "动画",
      "pairs": [
        {
          "source": { "title": "千与千寻", "year": "2001", "tmdbId": 129 },
          "recommend": { "title": "红海龟", "year": "2016", "tmdbId": 354110 },
          "reason": "如果你为宫崎骏笔下那个亦幻亦真的世界所迷醉，高畑勋（吉卜力工作室）的《红海龟》用极简的叙事和无声的海洋寓言带给你同样深沉的心灵触动。全片无对白，仅凭画面与音乐讲述一个人与自然相遇的史诗，留白中蕴藏着巨大的情感力量。"
        },
        {
          "source": { "title": "机器人总动员", "year": "2008", "tmdbId": 10681 },
          "recommend": { "title": "未来学大会", "year": "2013", "tmdbId": 105530 },
          "reason": "《机器人总动员》用瓦力的眼睛审视消费主义与人类未来，而《未来学大会》将这种批判推向了更激进的哲学维度。真人与动画交织，探讨意识上传、记忆数字化与身份边界的终极命题，是一部为所有热爱科幻的动画迷准备的脑内风暴。"
        }
      ]
    },
    {
      "name": "战争",
      "pairs": [
        {
          "source": { "title": "1917", "year": "2019", "tmdbId": 530915 },
          "recommend": { "title": "西线无战事", "year": "2022", "tmdbId": 928184 },
          "reason": "《1917》以一镜到底的沉浸式体验让你跟随主角穿行于一战的战壕与废墟，而《西线无战事》用最沉重克制的笔触揭示了战争的无意义与对人的异化。前者是技术奇迹与感官震撼，后者是灵魂叩问与历史反思——两部作品共同构成对一战最完整的影像回应。"
        },
        {
          "source": { "title": "拯救大兵瑞恩", "year": "1998", "tmdbId": 857 },
          "recommend": { "title": "细细的红线", "year": "1998", "tmdbId": 924 },
          "reason": "斯皮尔伯格的《拯救大兵瑞恩》用诺曼底登陆的经典开场重新定义了战争片的视听语言，而泰伦斯·马利克的《细细的红线》用诗意的镜头追问战争的意义与自然的永恒。两部作品同年上映，同以二战为背景，却走向了完全相反的美学方向——前者是写实主义的巅峰，后者是印象派的杰作。"
        }
      ]
    },
    {
      "name": "犯罪",
      "pairs": [
        {
          "source": { "title": "教父", "year": "1972", "tmdbId": 238 },
          "recommend": { "title": "美国往事", "year": "1984", "tmdbId": 311 },
          "reason": "《教父》与《美国往事》是黑帮电影的两座不可逾越的高峰。后者用更漫长的时间跨度、更伤感的叙事笔触，书写了犹太移民在美国半个世纪的浮沉史诗。如果你着迷于科莱昂家族的权力传承与家族羁绊，面条和麦克斯跨越数十年的恩怨纠葛会让你在片尾长叹不已。"
        },
        {
          "source": { "title": "无间道", "year": "2002", "tmdbId": 10775 },
          "recommend": { "title": "新世界", "year": "2013", "tmdbId": 127229 },
          "reason": "《无间道》中的卧底困局在《新世界》中被赋予了更极端、更暴烈的韩国式表达。如果你喜欢陈永仁与刘建明之间那种身份错位的宿命感，这部被誉为「韩版无间道」的电影将卧底题材推向了更暗黑的维度——背叛与忠诚的边界在这里被彻底模糊。"
        }
      ]
    },
    {
      "name": "剧情",
      "pairs": [
        {
          "source": { "title": "楚门的世界", "year": "1998", "tmdbId": 37165 },
          "recommend": { "title": "机械姬", "year": "2015", "tmdbId": 264660 },
          "reason": "《楚门的世界》对真实性的追问在《机械姬》中得到了AI视角的全新演绎：前者发现自己的人生是一场直播秀，后者在封闭空间中进行着关于意识的终极图灵测试。两部电影都让你走出影院后重新审视——什么是真实？谁在观察你？而自由又意味着什么？"
        }
      ]
    },
    {
      "name": "奇幻",
      "pairs": [
        {
          "source": { "title": "指环王：护戒使者", "year": "2001", "tmdbId": 120 },
          "recommend": { "title": "绿骑士", "year": "2021", "tmdbId": 617505 },
          "reason": "如果你沉醉于中土世界的宏大冒险，《绿骑士》用完全不同的美学带你进入亚瑟王传说中的奇幻疆域——极简、诡异、充满象征意味。它没有《护戒使者》的壮阔战役，却用每一次静谧的镜头和每一帧精妙的构图传递出同等的史诗感与宿命感。"
        }
      ]
    }
  ]
}
